{
  "accounts": [
    {
      "username": "admin123",
      "password": "admin123",
      "id": "33ba"
    },
    {
      "username": "admin234",
      "password": "admin234",
      "id": "2f79"
    },
    {
      "username": "admin345",
      "password": "admin345",
      "id": "76c1"
    },
    {
      "id": "ce19",
      "username": "admin",
      "password": "admin"
    },
    {
      "id": "3de5",
      "username": "",
      "password": ""
    },
    {
      "id": "5e09",
      "username": "admin2",
      "password": "admin2"
    },
    {
      "id": "0494",
      "username": "user1",
      "password": "user1"
    }
  ],
  "profile": {
    "name": "typicode"
  }
}